developing_agentic_ai/__init__.py
developing_agentic_ai/_version.py
developing_agentic_ai/chatbot.py
developing_agentic_ai/tools.py
developing_agentic_ai/utils.py
developing_agentic_ai/datasets/__init__.py
developing_agentic_ai/datasets/jailbreak.py
developing_agentic_ai-0.1.2.dist-info/licenses/LICENSE
developing_agentic_ai-0.1.2.dist-info/METADATA
developing_agentic_ai-0.1.2.dist-info/WHEEL
developing_agentic_ai-0.1.2.dist-info/top_level.txt
developing_agentic_ai-0.1.2.dist-info/RECORD
